kivy_deps/__init__.py
kivy_deps/sdl3_dev/__init__.py
kivy_deps_sdl3_dev-0.0.10.data/data/include/SDL3/SDL.h
kivy_deps_sdl3_dev-0.0.10.data/data/include/SDL3/SDL_assert.h
kivy_deps_sdl3_dev-0.0.10.data/data/include/SDL3/SDL_asyncio.h
kivy_deps_sdl3_dev-0.0.10.data/data/include/SDL3/SDL_atomic.h
kivy_deps_sdl3_dev-0.0.10.data/data/include/SDL3/SDL_audio.h
kivy_deps_sdl3_dev-0.0.10.data/data/include/SDL3/SDL_begin_code.h
kivy_deps_sdl3_dev-0.0.10.data/data/include/SDL3/SDL_bits.h
kivy_deps_sdl3_dev-0.0.10.data/data/include/SDL3/SDL_blendmode.h
kivy_deps_sdl3_dev-0.0.10.data/data/include/SDL3/SDL_camera.h
kivy_deps_sdl3_dev-0.0.10.data/data/include/SDL3/SDL_clipboard.h
kivy_deps_sdl3_dev-0.0.10.data/data/include/SDL3/SDL_close_code.h
kivy_deps_sdl3_dev-0.0.10.data/data/include/SDL3/SDL_copying.h
kivy_deps_sdl3_dev-0.0.10.data/data/include/SDL3/SDL_cpuinfo.h
kivy_deps_sdl3_dev-0.0.10.data/data/include/SDL3/SDL_dialog.h
kivy_deps_sdl3_dev-0.0.10.data/data/include/SDL3/SDL_egl.h
kivy_deps_sdl3_dev-0.0.10.data/data/include/SDL3/SDL_endian.h
kivy_deps_sdl3_dev-0.0.10.data/data/include/SDL3/SDL_error.h
kivy_deps_sdl3_dev-0.0.10.data/data/include/SDL3/SDL_events.h
kivy_deps_sdl3_dev-0.0.10.data/data/include/SDL3/SDL_filesystem.h
kivy_deps_sdl3_dev-0.0.10.data/data/include/SDL3/SDL_gamepad.h
kivy_deps_sdl3_dev-0.0.10.data/data/include/SDL3/SDL_gpu.h
kivy_deps_sdl3_dev-0.0.10.data/data/include/SDL3/SDL_guid.h
kivy_deps_sdl3_dev-0.0.10.data/data/include/SDL3/SDL_haptic.h
kivy_deps_sdl3_dev-0.0.10.data/data/include/SDL3/SDL_hidapi.h
kivy_deps_sdl3_dev-0.0.10.data/data/include/SDL3/SDL_hints.h
kivy_deps_sdl3_dev-0.0.10.data/data/include/SDL3/SDL_init.h
kivy_deps_sdl3_dev-0.0.10.data/data/include/SDL3/SDL_intrin.h
kivy_deps_sdl3_dev-0.0.10.data/data/include/SDL3/SDL_iostream.h
kivy_deps_sdl3_dev-0.0.10.data/data/include/SDL3/SDL_joystick.h
kivy_deps_sdl3_dev-0.0.10.data/data/include/SDL3/SDL_keyboard.h
kivy_deps_sdl3_dev-0.0.10.data/data/include/SDL3/SDL_keycode.h
kivy_deps_sdl3_dev-0.0.10.dist-info/METADATA
kivy_deps_sdl3_dev-0.0.10.dist-info/WHEEL
kivy_deps_sdl3_dev-0.0.10.dist-info/top_level.txt
kivy_deps_sdl3_dev-0.0.10.dist-info/RECORD
